{
  "doc_id": "string",
  "doc_name": "string",
  "doc_title": "string",
  "doc_description": "string",
  "number_of_pages": 0,
  "created_at": 0,
  "modify_at": 0,
  "owner_id": "string",
  "cover_img": "https://example.com/",
  "is_published": true,
  "tts_ready": true,
  "pages": [
    {
      "file_name": "string",
      "page_id": "string",
      "page_num": 0,
      "master_doc": "string",
      "elements": {
        "image": "string",
        "img_url": "https://example.com/",
        "lang": "string",
        "lang_accuracy": 0,
        "text": "string",
        "txt_file_url": "https://example.com/",
        "tts_url": "https://example.com/",
        "img_text": "string",
        "img_tts_url": "https://example.com/",
        "create_img_tts": true,
        "create_txt_tts": true
      }
    }
  ]
}
